GptCode/__init__.py
GptCode/gpt.py
GptCode-1.0.8.dist-info/METADATA
GptCode-1.0.8.dist-info/WHEEL
GptCode-1.0.8.dist-info/top_level.txt
GptCode-1.0.8.dist-info/RECORD
